[{"user_id": 4893, "stars": [{"date_created": 1298998721.2003241, "user_id": 16709}], "topic_id": 3507, "date_created": 1297339228.8479259, "message": "W\u00e4re Convore vielleicht ein Ersatz f\u00fcr die Mailinglist, zumindest was die Diskussionen angeht? Ank\u00fcndigungen machen ja auf der Mailinglist absolut Sinn, aber vielleicht k\u00f6nnten wir hier eine etwas gr\u00f6\u00dfere Beteiligung bei den Diskussionen erreichen?", "group_id": 1616, "id": 68630}, {"user_id": 5502, "stars": [], "topic_id": 3507, "date_created": 1297344640.4249661, "message": "schaut gut aus", "group_id": 1616, "id": 69174}, {"user_id": 16709, "stars": [], "topic_id": 3507, "date_created": 1298998684.184515, "message": "mir gef\u00e4llt das ganz gut", "group_id": 1616, "id": 236263}, {"user_id": 4893, "stars": [], "topic_id": 3507, "date_created": 1298999582.7271221, "message": "Ich finde es vor allem f\u00fcr echte Diskussionen ganz praktisch. Zumindest bei unserer Mailinglist findet das ja leider derzeit noch effektiv nicht statt :-) Ich habe jedenfalls mal einen Link auf diese Gruppe auf pygraz.org gestellt :-)", "group_id": 1616, "id": 236307}, {"user_id": 16709, "stars": [], "topic_id": 3507, "date_created": 1299000332.190438, "message": "\u00fcber den Link bin ich gerade hergekommen :-)", "group_id": 1616, "id": 236340}]