[{"user_id": 36609, "stars": [], "topic_id": 39955, "date_created": 1308642390.884897, "message": "I wanted to use Convore API https://convore.com/api/ for my startup - vridelalong.org ... can someone please help, how to start? Is it free for use? Any limitations?", "group_id": 88, "id": 1446417}, {"user_id": 2597, "stars": [], "topic_id": 39955, "date_created": 1308668081.8356471, "message": "yes it's free of use, you should first familiarize yourself with REST API and JSON", "group_id": 88, "id": 1449032}, {"user_id": 2597, "stars": [], "topic_id": 39955, "date_created": 1308671887.4727449, "message": "@italiano40 ok nvm", "group_id": 88, "id": 1449625}, {"user_id": 4149, "stars": [], "topic_id": 39955, "date_created": 1308671869.6883969, "message": "@equinox no, the domain in the post vridelalong.org", "group_id": 88, "id": 1449622}, {"user_id": 4149, "stars": [], "topic_id": 39955, "date_created": 1308671507.308553, "message": "also your web site is down", "group_id": 88, "id": 1449575}, {"user_id": 36609, "stars": [], "topic_id": 39955, "date_created": 1309068849.190836, "message": "Thanks for the info, I am exploring it further...", "group_id": 88, "id": 1487532}, {"user_id": 36609, "stars": [], "topic_id": 39955, "date_created": 1309068860.840677, "message": "Yes, my website is www.vridealong.org", "group_id": 88, "id": 1487533}]