[{"user_id": 25716, "stars": [], "topic_id": 46214, "date_created": 1317871144.999372, "message": "Hola a todos. Mucho tiempo sin vernos! Espero que todos tengan mucho exito, etc ;)\n\nQue estas haciendo para convertir visitantes e incrementar la confianza de tu startup?\n\nTengo una startup de live chat aqui en mexico, y quiero que me ayuden los otros startups aqui. Los startups en mexico no tiene mucho capital como EU, Europa, etc, y pienso que lo minimo que yo puedo hacer es regalar un live chat gratis de por vida para startups aqui (uno startup a otro).\n\nUn ejemplo de startup mexicana que uso eso live chat es metriclytics: http://www.metriclytics.com\n\nQuiero mas ayuda :) La informacion del cSupport esta aqui: http://csupporthq.com\n\nSi tienen algun interes, escribeme acerca de tu startup y yo te regalar\u00e9 una suscripcion!\n\nTwitter: @cSupport_dk @ds_abcel\nContacto: http://csupport.com.mx/contacto/\nO escribeme aqui! Buenas noches!", "group_id": 965, "id": 2289444}, {"user_id": 25716, "stars": [], "topic_id": 46214, "date_created": 1318045215.632601, "message": "wow, este foro ha muerto :O", "group_id": 965, "id": 2302903}, {"user_id": 27648, "stars": [], "topic_id": 46214, "date_created": 1318312415.6551831, "message": "Nosotros utilizamos el live chat bastante, practicamente 24x7 en 2 de nuestras marcas. nos gustar\u00eda probar alguno de una startup mexicana", "group_id": 965, "id": 2323119}, {"user_id": 25716, "stars": [], "topic_id": 46214, "date_created": 1318384349.7752299, "message": "Bueno. Espero que esto puede ayudar las startups mexicanas que no tiene mucho fundos :) Te envio una mensaje", "group_id": 965, "id": 2329145}, {"user_id": 25716, "stars": [], "topic_id": 46214, "date_created": 1318385958.38131, "message": "Para todos: Necesito el nombre, URL y e-mail de contacto del startup para hacer una cuenta", "group_id": 965, "id": 2329408}]