[{"user_id": 1, "stars": [], "topic_id": 1807, "date_created": 1297062741.9764969, "message": "watching...this from yesterday?", "group_id": 11, "id": 47093}, {"user_id": 227, "stars": [], "topic_id": 1807, "date_created": 1297062911.8696611, "message": "a. John waters is fucking epic. b. nicki minaj is fucking epic. c. the three lonely island guys together doing the creep thing is beyond priceless.", "group_id": 11, "id": 47102}, {"user_id": 227, "stars": [], "topic_id": 1807, "date_created": 1297062716.792506, "message": "http://www.hulu.com/watch/211060/saturday-night-live-snl-digital-short-the-creep is fucking awesome.", "group_id": 11, "id": 47091}, {"user_id": 227, "stars": [], "topic_id": 1807, "date_created": 1297062752.604434, "message": "No, from the episode with Zuck.", "group_id": 11, "id": 47094}, {"user_id": 1, "stars": [], "topic_id": 1807, "date_created": 1297062853.6207471, "message": "haha, gets good halfway through :)", "group_id": 11, "id": 47101}]