[{"user_id": 7, "stars": [], "topic_id": 1451, "date_created": 1296351909.4018879, "message": "Both summits + full sprints", "group_id": 81, "id": 37825}, {"user_id": 7, "stars": [{"date_created": 1296351923.310591, "user_id": 219}], "topic_id": 1451, "date_created": 1296351911.419081, "message": "so fucking excited", "group_id": 81, "id": 37826}, {"user_id": 1, "stars": [], "topic_id": 1451, "date_created": 1296351890.8814051, "message": "Woot!", "group_id": 81, "id": 37822}, {"user_id": 7, "stars": [{"date_created": 1296351910.5874989, "user_id": 1}], "topic_id": 1451, "date_created": 1296351905.8609409, "message": "Me", "group_id": 81, "id": 37823}, {"user_id": 177, "stars": [], "topic_id": 1451, "date_created": 1296354259.9092541, "message": "I'll be there! :D First time too!", "group_id": 81, "id": 37961}, {"user_id": 1, "stars": [], "topic_id": 1451, "date_created": 1296351859.910372, "message": "I am!", "group_id": 81, "id": 37819}, {"user_id": 1, "stars": [], "topic_id": 1451, "date_created": 1296351865.64217, "message": "Anyone else here gonna be there?", "group_id": 81, "id": 37820}, {"user_id": 219, "stars": [{"date_created": 1296351882.7626531, "user_id": 1}], "topic_id": 1451, "date_created": 1296351878.6496489, "message": "me :)", "group_id": 81, "id": 37821}, {"user_id": 7, "stars": [], "topic_id": 1451, "date_created": 1296352146.154398, "message": ":(", "group_id": 81, "id": 37831}, {"user_id": 216, "stars": [], "topic_id": 1451, "date_created": 1296351908.665946, "message": "Wish I could make it, but unfortunately it lost out this year.", "group_id": 81, "id": 37824}, {"user_id": 218, "stars": [], "topic_id": 1451, "date_created": 1296352238.0095789, "message": "Going to miss it this year. Starting a new gig in Seattle, WA and its just too soon after starting to take the time off.", "group_id": 81, "id": 37837}, {"user_id": 1, "stars": [], "topic_id": 1451, "date_created": 1296351918.775193, "message": "@asenchi Aww :(", "group_id": 81, "id": 37827}, {"user_id": 1, "stars": [], "topic_id": 1451, "date_created": 1296351931.081629, "message": "Ahh yeah, I can't make it to the sprints this year for the first time.", "group_id": 81, "id": 37828}, {"user_id": 1, "stars": [], "topic_id": 1451, "date_created": 1296352364.2820461, "message": "@justinlilly congrats on the new gig!", "group_id": 81, "id": 37838}, {"user_id": 1, "stars": [], "topic_id": 1451, "date_created": 1296354270.5557361, "message": "@bryan wootwoot!", "group_id": 81, "id": 37962}, {"user_id": 1, "stars": [], "topic_id": 1451, "date_created": 1296363059.937989, "message": "Whoa, kind of just realized how awesome that'll be!", "group_id": 81, "id": 38266}, {"user_id": 1, "stars": [], "topic_id": 1451, "date_created": 1296363125.722194, "message": "@alex I've spent the past few months of my life building a streamer :P", "group_id": 81, "id": 38268}, {"user_id": 7, "stars": [], "topic_id": 1451, "date_created": 1296363131.1660669, "message": "haha", "group_id": 81, "id": 38269}, {"user_id": 215, "stars": [{"date_created": 1296364264.5321939, "user_id": 1}], "topic_id": 1451, "date_created": 1296364110.4980879, "message": "make it possible to attach twitter keywords and flickr tags to topics and viola :-)", "group_id": 81, "id": 38270}, {"user_id": 1, "stars": [], "topic_id": 1451, "date_created": 1296364276.7209611, "message": "Yeah that's a great idea", "group_id": 81, "id": 38272}, {"user_id": 1, "stars": [], "topic_id": 1451, "date_created": 1296364316.079921, "message": "It's pretty much my favorite thing on Convore", "group_id": 81, "id": 38276}, {"user_id": 211, "stars": [{"date_created": 1296363011.9929309, "user_id": 7}], "topic_id": 1451, "date_created": 1296362979.634402, "message": "<-- can't wait.", "group_id": 81, "id": 38263}, {"user_id": 1, "stars": [{"date_created": 1296363013.077991, "user_id": 7}], "topic_id": 1451, "date_created": 1296363004.1425631, "message": "Me neither!", "group_id": 81, "id": 38264}, {"user_id": 1, "stars": [], "topic_id": 1451, "date_created": 1296363050.4638629, "message": "Actually I think Convore could be a pretty cool PyCon backchannel. A group for PyCon, topics for each talk, plus topics for like people wanting to go get food and stuff.", "group_id": 81, "id": 38265}, {"user_id": 7, "stars": [], "topic_id": 1451, "date_created": 1296363098.8070829, "message": "we not going to do the streamer this year?", "group_id": 81, "id": 38267}, {"user_id": 7, "stars": [], "topic_id": 1451, "date_created": 1296364265.6827829, "message": "@brosner you could alreayd write a bot for it I guess", "group_id": 81, "id": 38271}, {"user_id": 1, "stars": [], "topic_id": 1451, "date_created": 1296364288.485007, "message": "@brosner Oh you haven't seen evilbot have you?", "group_id": 81, "id": 38273}, {"user_id": 1, "stars": [], "topic_id": 1451, "date_created": 1296364290.1087649, "message": ":)", "group_id": 81, "id": 38274}, {"user_id": 1, "stars": [], "topic_id": 1451, "date_created": 1296364300.6375041, "message": "https://github.com/defunkt/evilbot", "group_id": 81, "id": 38275}, {"user_id": 205, "stars": [], "topic_id": 1451, "date_created": 1296369686.791153, "message": "/me is going \\o/", "group_id": 81, "id": 38299}, {"user_id": 208, "stars": [], "topic_id": 1451, "date_created": 1296422302.5366571, "message": "I'll be there with bells on.", "group_id": 81, "id": 38322}, {"user_id": 1, "stars": [], "topic_id": 1451, "date_created": 1296435489.75951, "message": "Found this http://us.pycon.org/2011/schedule/lists/talks/", "group_id": 81, "id": 38588}, {"user_id": 1, "stars": [], "topic_id": 1451, "date_created": 1296435441.4354801, "message": "Is there a published schedule?", "group_id": 81, "id": 38585}, {"user_id": 1, "stars": [], "topic_id": 1451, "date_created": 1296435447.1210699, "message": "I feel like I've seen one but now I can't find it", "group_id": 81, "id": 38586}, {"user_id": 1, "stars": [], "topic_id": 1451, "date_created": 1296435476.873107, "message": "I mean, like I think I've seen a calendar version", "group_id": 81, "id": 38587}, {"user_id": 7, "stars": [], "topic_id": 1451, "date_created": 1296436789.022285, "message": "No, there's only a schedule for tutorials thus far", "group_id": 81, "id": 38611}, {"user_id": 1, "stars": [], "topic_id": 1451, "date_created": 1296441912.8252571, "message": "@brosner awesome, thanks!", "group_id": 81, "id": 38749}, {"user_id": 215, "stars": [], "topic_id": 1451, "date_created": 1296441902.5191, "message": "@ericflo there will be a schedule one like http://us.pycon.org/2010/conference/schedule/ very soon.", "group_id": 81, "id": 38748}, {"user_id": 228, "stars": [{"date_created": 1296452686.8851211, "user_id": 1}], "topic_id": 1451, "date_created": 1296452675.115726, "message": "I'll be there/first time as well. Last day of tutorials and a day and a half of sprints.", "group_id": 81, "id": 38925}, {"user_id": 1, "stars": [], "topic_id": 1451, "date_created": 1296452692.768652, "message": "@jacob Woot!", "group_id": 81, "id": 38926}, {"user_id": 1, "stars": [], "topic_id": 1451, "date_created": 1296452777.5447011, "message": "Yeah, I really wish I could stay for the sprints :(", "group_id": 81, "id": 38928}, {"user_id": 1, "stars": [], "topic_id": 1451, "date_created": 1296452794.0688641, "message": "Have some Convore-related business that prevents me from staying though", "group_id": 81, "id": 38929}, {"user_id": 229, "stars": [{"date_created": 1296452766.6321831, "user_id": 1}], "topic_id": 1451, "date_created": 1296452748.006942, "message": "I'll be there for the main conference only, with @schmichael and @ericholscher. I'm really looking forward to it.", "group_id": 81, "id": 38927}, {"user_id": 229, "stars": [], "topic_id": 1451, "date_created": 1296453021.493937, "message": "@jacob Good question! Any day's good for me", "group_id": 81, "id": 38944}, {"user_id": 229, "stars": [], "topic_id": 1451, "date_created": 1296453124.7781351, "message": "I wasn't impressed with the restaurants & bars I went to (although the one microbrewery nearby was decent enough as a backup).", "group_id": 81, "id": 38949}, {"user_id": 7, "stars": [], "topic_id": 1451, "date_created": 1296453352.540417, "message": "don't know if any of you were there though", "group_id": 81, "id": 38962}, {"user_id": 1, "stars": [], "topic_id": 1451, "date_created": 1296453138.5379429, "message": "Plus there was Chick-fil-A", "group_id": 81, "id": 38950}, {"user_id": 7, "stars": [], "topic_id": 1451, "date_created": 1296453422.7889211, "message": "and convore needs to stop distracting me I need to prove that I exist (no joke)", "group_id": 81, "id": 38973}, {"user_id": 205, "stars": [{"date_created": 1296453055.144304, "user_id": 1}], "topic_id": 1451, "date_created": 1296453050.9400289, "message": "/me gets excited for pycon :)", "group_id": 81, "id": 38945}, {"user_id": 228, "stars": [], "topic_id": 1451, "date_created": 1296452957.4459119, "message": "@robotadam when does a whisky-seeking adventure occur? and at what regular interval?", "group_id": 81, "id": 38938}, {"user_id": 228, "stars": [], "topic_id": 1451, "date_created": 1296453088.8617411, "message": "have to get dad a present somehow and he loves nostalgic coke 'verts.", "group_id": 81, "id": 38947}, {"user_id": 228, "stars": [], "topic_id": 1451, "date_created": 1296453164.327028, "message": "i'll see what i can find through my foodie-network. there has to be at least one or two southern-loving people that leave new orleans.", "group_id": 81, "id": 38953}, {"user_id": 1, "stars": [], "topic_id": 1451, "date_created": 1296453166.9299331, "message": "@robotadam Yes, yes I do.", "group_id": 81, "id": 38954}, {"user_id": 7, "stars": [], "topic_id": 1451, "date_created": 1296453347.9049881, "message": "That gastropubd we went to was pretty solid", "group_id": 81, "id": 38961}, {"user_id": 228, "stars": [], "topic_id": 1451, "date_created": 1296453068.4705081, "message": "i've never been to atlanta (outside of the airport) either, so I'll be lazywebbing the best food/booze in the area. the only touristy thing i'll probably do is the coke building", "group_id": 81, "id": 38946}, {"user_id": 1, "stars": [], "topic_id": 1451, "date_created": 1296453114.9905159, "message": "I remember there was like a food court attached to the hotel in ATL, and it was so bad because we all kept just going there instead of going out for real food, haha", "group_id": 81, "id": 38948}, {"user_id": 229, "stars": [{"date_created": 1296453163.5504129, "user_id": 1}], "topic_id": 1451, "date_created": 1296453157.592289, "message": "Oh, you mean Jesus Chicken.", "group_id": 81, "id": 38952}, {"user_id": 205, "stars": [], "topic_id": 1451, "date_created": 1296453169.3821371, "message": "Just sayin': http://farm1.static.flickr.com/190/501203343_e51d02cff9.jpg", "group_id": 81, "id": 38955}, {"user_id": 228, "stars": [], "topic_id": 1451, "date_created": 1296453386.86216, "message": "@alex they let you into micropubs?", "group_id": 81, "id": 38966}, {"user_id": 228, "stars": [], "topic_id": 1451, "date_created": 1296453392.4255791, "message": "did they have kid's meals?", "group_id": 81, "id": 38967}, {"user_id": 7, "stars": [], "topic_id": 1451, "date_created": 1296453400.584779, "message": "@jacob not a micropub, a gastropub", "group_id": 81, "id": 38968}, {"user_id": 7, "stars": [], "topic_id": 1451, "date_created": 1296453407.6107619, "message": "don't ask me WTF that means", "group_id": 81, "id": 38970}, {"user_id": 228, "stars": [], "topic_id": 1451, "date_created": 1296453417.940325, "message": "@alex they let you into gastropubs?", "group_id": 81, "id": 38972}, {"user_id": 228, "stars": [], "topic_id": 1451, "date_created": 1296453439.7044251, "message": "just write \"cogito\" and be done with it", "group_id": 81, "id": 38976}, {"user_id": 7, "stars": [], "topic_id": 1451, "date_created": 1296453444.98561, "message": "@jacob clerical error no doubt", "group_id": 81, "id": 38977}, {"user_id": 210, "stars": [{"date_created": 1296455076.4115551, "user_id": 1}, {"date_created": 1296455095.823297, "user_id": 228}, {"date_created": 1296455117.604306, "user_id": 7}, {"date_created": 1296460066.8550179, "user_id": 206}], "topic_id": 1451, "date_created": 1296455068.0207231, "message": "I will be there.", "group_id": 81, "id": 39249}, {"user_id": 7, "stars": [], "topic_id": 1451, "date_created": 1296455124.8547349, "message": "@daniellindsley oh you were at the gastropub", "group_id": 81, "id": 39256}, {"user_id": 210, "stars": [{"date_created": 1296455229.4334731, "user_id": 232}], "topic_id": 1451, "date_created": 1296455189.9045889, "message": "Can we have a lulz Convore group?", "group_id": 81, "id": 39265}, {"user_id": 7, "stars": [{"date_created": 1296455226.432807, "user_id": 1}], "topic_id": 1451, "date_created": 1296455219.4504731, "message": "I want notifcications when my friends create groups btw", "group_id": 81, "id": 39270}, {"user_id": 210, "stars": [], "topic_id": 1451, "date_created": 1296455744.792558, "message": "I accidentally a https://convore.com/lulz/.", "group_id": 81, "id": 39360}, {"user_id": 210, "stars": [{"date_created": 1296455138.7046571, "user_id": 1}, {"date_created": 1296455146.067529, "user_id": 2}, {"date_created": 1296455189.3754179, "user_id": 228}, {"date_created": 1296456024.73369, "user_id": 211}, {"date_created": 1296529404.8784261, "user_id": 177}], "topic_id": 1451, "date_created": 1296455133.987021, "message": "Y U STAR ME?", "group_id": 81, "id": 39258}, {"user_id": 1, "stars": [{"date_created": 1296455182.391844, "user_id": 7}, {"date_created": 1296815637.654355, "user_id": 213}], "topic_id": 1451, "date_created": 1296455166.4403989, "message": "http://www.katiebailey.co.uk/images/img_girl_pointing.jpg", "group_id": 81, "id": 39263}, {"user_id": 7, "stars": [], "topic_id": 1451, "date_created": 1296455211.688117, "message": "I'm always down for lulz", "group_id": 81, "id": 39269}, {"user_id": 7, "stars": [{"date_created": 1296455276.4793451, "user_id": 2}], "topic_id": 1451, "date_created": 1296455232.069025, "message": "I also wouldn't mind local friends, since I'm not going to friend all you fuckers on fb", "group_id": 81, "id": 39271}, {"user_id": 7, "stars": [], "topic_id": 1451, "date_created": 1296455240.711446, "message": "so nvm", "group_id": 81, "id": 39274}, {"user_id": 1, "stars": [], "topic_id": 1451, "date_created": 1296455248.3252771, "message": "@daniellindsley Yeah, you can create any group you want", "group_id": 81, "id": 39275}, {"user_id": 7, "stars": [{"date_created": 1297311656.924041, "user_id": 4546}], "topic_id": 1451, "date_created": 1296455263.8285079, "message": "@ericflo Yeah basically I just want to follow the cool kids, plez make that easy", "group_id": 81, "id": 39276}, {"user_id": 210, "stars": [], "topic_id": 1451, "date_created": 1296455129.548317, "message": "WTF?", "group_id": 81, "id": 39257}, {"user_id": 1, "stars": [], "topic_id": 1451, "date_created": 1296455233.5578871, "message": "@alex That's a great point", "group_id": 81, "id": 39272}, {"user_id": 7, "stars": [], "topic_id": 1451, "date_created": 1296455237.117892, "message": "though I guess I follow you on twitter", "group_id": 81, "id": 39273}, {"user_id": 1, "stars": [], "topic_id": 1451, "date_created": 1296455267.3960559, "message": "@alex We want to have local friends eventually. Just not for the first release.", "group_id": 81, "id": 39277}, {"user_id": 7, "stars": [{"date_created": 1296455286.1980619, "user_id": 1}], "topic_id": 1451, "date_created": 1296455281.212008, "message": "@ericflo that's fine, once I remembered twitter followers worked I don't care so much", "group_id": 81, "id": 39279}, {"user_id": 177, "stars": [], "topic_id": 1451, "date_created": 1296529429.001308, "message": "@evilbot image me y u star me", "group_id": 81, "id": 40325}, {"user_id": 218, "stars": [], "topic_id": 1451, "date_created": 1296530956.9361551, "message": "@evilbot image me star eyes", "group_id": 81, "id": 40347}, {"user_id": 218, "stars": [], "topic_id": 1451, "date_created": 1296530964.6178031, "message": "/me wants an evil bot.", "group_id": 81, "id": 40348}, {"user_id": 1, "stars": [], "topic_id": 1451, "date_created": 1296531040.955286, "message": ":)", "group_id": 81, "id": 40351}, {"user_id": 1, "stars": [], "topic_id": 1451, "date_created": 1296531044.314136, "message": "I want evilbot too", "group_id": 81, "id": 40352}, {"user_id": 7, "stars": [], "topic_id": 1451, "date_created": 1296687828.3278489, "message": "http://www.google.com/moderator/#15/e=5615c&t=5615c.40", "group_id": 81, "id": 43176}, {"user_id": 228, "stars": [], "topic_id": 1451, "date_created": 1297118263.657392, "message": "hey. who wants to share a room with me in atlanta?!", "group_id": 81, "id": 48158}, {"user_id": 218, "stars": [], "topic_id": 1451, "date_created": 1297118377.1678481, "message": "@jacob  @bastih is looking for a roomie, last I heard.", "group_id": 81, "id": 48161}, {"user_id": 228, "stars": [], "topic_id": 1451, "date_created": 1297118547.5706971, "message": "@justinlilly sweet thanks for the notice. i'll try and ping him on the tweetverse", "group_id": 81, "id": 48170}, {"user_id": 7, "stars": [{"date_created": 1297134758.6059339, "user_id": 1}], "topic_id": 1451, "date_created": 1297134472.019614, "message": "If you haven't already, go vote: http://www.google.com/moderator/#15/e=5615c&t=5615c.40", "group_id": 81, "id": 48663}, {"user_id": 7, "stars": [], "topic_id": 1451, "date_created": 1297135154.751276, "message": "oh hey I linked that like 4 lines up", "group_id": 81, "id": 48693}, {"user_id": 1, "stars": [], "topic_id": 1451, "date_created": 1297135413.1613431, "message": "How convenient that I just built a ban tool...", "group_id": 81, "id": 48711}, {"user_id": 216, "stars": [], "topic_id": 1451, "date_created": 1297135392.904206, "message": "spammer!", "group_id": 81, "id": 48710}, {"user_id": 229, "stars": [{"date_created": 1297284042.4569149, "user_id": 2113}], "topic_id": 1451, "date_created": 1297137568.10606, "message": "Just getting this out in people's minds a little early: http://www.forpeatsake.com/Images/Bottles/Red_Breast/Red_Breast_Red_Breast_12_Year_Old_12_.jpg", "group_id": 81, "id": 48871}, {"user_id": 561, "stars": [], "topic_id": 1451, "date_created": 1297141899.994709, "message": "I'm going to pycon.", "group_id": 81, "id": 49041}, {"user_id": 216, "stars": [], "topic_id": 1451, "date_created": 1297142039.9895401, "message": "@robotadam Red Breast is awesome.", "group_id": 81, "id": 49047}, {"user_id": 228, "stars": [], "topic_id": 1451, "date_created": 1297188252.7747171, "message": "darnit bastih found someone =(", "group_id": 81, "id": 49369}, {"user_id": 218, "stars": [], "topic_id": 1451, "date_created": 1297188406.241498, "message": "@jacob http://us.pycon.org/2011/tickets/room_sharing/", "group_id": 81, "id": 49371}, {"user_id": 228, "stars": [], "topic_id": 1451, "date_created": 1297188480.569968, "message": "\"Vicky vixter@gmail.com have one Female roommate already, can take 1 or 2 more\"", "group_id": 81, "id": 49374}, {"user_id": 228, "stars": [], "topic_id": 1451, "date_created": 1297188488.790148, "message": "i smell a ladybugs esque comedy coming on!", "group_id": 81, "id": 49375}, {"user_id": 212, "stars": [], "topic_id": 1451, "date_created": 1297208236.448853, "message": "@jacob we're looking for another roomie, if you don't mind having 4 people in the room", "group_id": 81, "id": 50006}, {"user_id": 228, "stars": [], "topic_id": 1451, "date_created": 1297209087.289355, "message": "@gg four people in the room translates to \"cheaper for me\" to me. double + two cots?", "group_id": 81, "id": 50028}, {"user_id": 927, "stars": [], "topic_id": 1451, "date_created": 1297277529.7181771, "message": "Anything interesting planned for the sprints?", "group_id": 81, "id": 51993}, {"user_id": 844, "stars": [], "topic_id": 1451, "date_created": 1297279244.1736181, "message": "I'm staying in a cheapo Motel 6 about 3 blocks away will take 1 roomate  @$40/night", "group_id": 81, "id": 52915}, {"user_id": 228, "stars": [], "topic_id": 1451, "date_created": 1297280228.9047711, "message": "@dartdog in! i'l have to figure out the 9th and 10th. mayhaps that motel6 still has space? we could maybe extend the room and i could pay in full. or just take another room", "group_id": 81, "id": 53372}, {"user_id": 228, "stars": [], "topic_id": 1451, "date_created": 1297279193.3491859, "message": "@dartdog looking forward to seeing you again! the round-robin table talk we had two djangocon ago at jake was quite interesting", "group_id": 81, "id": 52894}, {"user_id": 844, "stars": [], "topic_id": 1451, "date_created": 1297279986.966377, "message": "@jacob 11th to 15th (leave 16th)", "group_id": 81, "id": 53242}, {"user_id": 228, "stars": [], "topic_id": 1451, "date_created": 1297279168.9885781, "message": "@gg ping again. let me know if the room is still available", "group_id": 81, "id": 52885}, {"user_id": 1264, "stars": [], "topic_id": 1451, "date_created": 1297280650.2809989, "message": "Anyone airbnb'ing?", "group_id": 81, "id": 53570}, {"user_id": 844, "stars": [], "topic_id": 1451, "date_created": 1297279130.806644, "message": "Looking forward to it.. see y'all there", "group_id": 81, "id": 52864}, {"user_id": 228, "stars": [], "topic_id": 1451, "date_created": 1297279816.6299341, "message": "@dartdog what nights?", "group_id": 81, "id": 53157}, {"user_id": 1167, "stars": [], "topic_id": 1451, "date_created": 1297279808.952812, "message": "@alex @ericflo so the djangodose streamer will be up for pycon? Otherwise I can make one but it's best not to duplicate effort :)", "group_id": 81, "id": 53154}, {"user_id": 1333, "stars": [], "topic_id": 1451, "date_created": 1297281732.605653, "message": "to my surprise, it looks like I may actually be at PyCon...", "group_id": 81, "id": 54147}, {"user_id": 1264, "stars": [], "topic_id": 1451, "date_created": 1297280472.570154, "message": "Going to PyCon.", "group_id": 81, "id": 53486}, {"user_id": 844, "stars": [], "topic_id": 1451, "date_created": 1297281455.922462, "message": "@jacob suggest you contact them directly http://www.motel6.com/reservations/motel_detail.aspx?num=4496", "group_id": 81, "id": 54034}, {"user_id": 844, "stars": [], "topic_id": 1451, "date_created": 1297282184.184592, "message": "@jacob you are good for my dates", "group_id": 81, "id": 54326}, {"user_id": 228, "stars": [], "topic_id": 1451, "date_created": 1297281555.979286, "message": "@dartdog will do! am i good for your dates though?", "group_id": 81, "id": 54082}, {"user_id": 844, "stars": [], "topic_id": 1451, "date_created": 1297281995.0725391, "message": "your good", "group_id": 81, "id": 54253}, {"user_id": 1, "stars": [], "topic_id": 1451, "date_created": 1297283253.2308559, "message": "Yeah. PyCon is going to be awesome, can't wait!", "group_id": 81, "id": 54857}, {"user_id": 1874, "stars": [], "topic_id": 1451, "date_created": 1297282918.1840849, "message": "@jacob sorry", "group_id": 81, "id": 54687}, {"user_id": 212, "stars": [], "topic_id": 1451, "date_created": 1297283320.3016269, "message": "also, if anyone has space during the sprints (beyond the 14th) two myself and @wolever are looking", "group_id": 81, "id": 54905}, {"user_id": 1874, "stars": [], "topic_id": 1451, "date_created": 1297282957.262568, "message": "looking forward to pycon, hooray :D", "group_id": 81, "id": 54717}, {"user_id": 212, "stars": [], "topic_id": 1451, "date_created": 1297283252.400862, "message": "we're in the conference hotel 9th to 14th, if you're still interested (and it'll be $25ish per night)", "group_id": 81, "id": 54855}, {"user_id": 212, "stars": [], "topic_id": 1451, "date_created": 1297283142.7694521, "message": "@jacob sorry i missed that...i guess convore doesn't email me when I get mentioned :)", "group_id": 81, "id": 54813}, {"user_id": 228, "stars": [], "topic_id": 1451, "date_created": 1297288139.6044941, "message": "@dartdog i leave the night of the 15th btw, so you'll have a night without my insanity =)", "group_id": 81, "id": 57913}, {"user_id": 1215, "stars": [], "topic_id": 1451, "date_created": 1297287765.592782, "message": "hotels are so expensive\r\nI wonder if there's a nice place to stay", "group_id": 81, "id": 57624}, {"user_id": 228, "stars": [], "topic_id": 1451, "date_created": 1297288110.6190641, "message": "@gg: no worries, dartdog brought the hookup--if you'd want, i could crash with you guys the 9th and the 10th though.", "group_id": 81, "id": 57884}, {"user_id": 2852, "stars": [], "topic_id": 1451, "date_created": 1297288875.75525, "message": "Convinced my employer to send me to PyCon all the way from Norway :)", "group_id": 81, "id": 58431}, {"user_id": 212, "stars": [], "topic_id": 1451, "date_created": 1297289355.631995, "message": "@jacob yea, the 9th and 10th should work: looks like one of the other guys isn't going to be arriving until the 10th now, so you'll be able to stake your claim to a real bed :)", "group_id": 81, "id": 58708}, {"user_id": 228, "stars": [], "topic_id": 1451, "date_created": 1297290346.6224401, "message": "@gg sweet! shoot me an email with your info and i'll reply with mine. elitist [at] gmail [dot] com", "group_id": 81, "id": 59103}, {"user_id": 1535, "stars": [], "topic_id": 1451, "date_created": 1297292759.0610931, "message": "I will be at pycon.", "group_id": 81, "id": 59751}, {"user_id": 3447, "stars": [], "topic_id": 1451, "date_created": 1297294340.683135, "message": "Me.", "group_id": 81, "id": 60153}, {"user_id": 844, "stars": [], "topic_id": 1451, "date_created": 1297303460.334028, "message": "@jacob drop me an e-mail confirming and contact details tombrander  @  tombrander.com thnks", "group_id": 81, "id": 62947}, {"user_id": 1376, "stars": [], "topic_id": 1451, "date_created": 1297306593.838721, "message": "I'll be there with Scotch on.", "group_id": 81, "id": 63793}, {"user_id": 1736, "stars": [], "topic_id": 1451, "date_created": 1297306693.4427891, "message": "I have the bad luck of presenting at the same time as @jacobian, boohiss.", "group_id": 81, "id": 63808}, {"user_id": 1963, "stars": [], "topic_id": 1451, "date_created": 1297310235.0433769, "message": "Driving down from NC w/ a bunch of coworkers :)", "group_id": 81, "id": 64503}, {"user_id": 1398, "stars": [], "topic_id": 1451, "date_created": 1297310803.3649869, "message": "I will be at pycon!", "group_id": 81, "id": 64567}, {"user_id": 1963, "stars": [], "topic_id": 1451, "date_created": 1297310195.9371779, "message": "I'll be there.", "group_id": 81, "id": 64494}, {"user_id": 3946, "stars": [], "topic_id": 1451, "date_created": 1297310571.298059, "message": "I'll walk there, from pretty much there.", "group_id": 81, "id": 64549}, {"user_id": 1916, "stars": [], "topic_id": 1451, "date_created": 1297310859.9827919, "message": "I'll be there for the conference and 2 sprint days. Can't wait.", "group_id": 81, "id": 64573}, {"user_id": 4512, "stars": [], "topic_id": 1451, "date_created": 1297310831.630933, "message": "I'll be at pycon also!   I heard pydanny is buying me a beer for my birthday!", "group_id": 81, "id": 64571}, {"user_id": 3946, "stars": [], "topic_id": 1451, "date_created": 1297313122.447871, "message": "@bitprophet !", "group_id": 81, "id": 64889}, {"user_id": 4156, "stars": [], "topic_id": 1451, "date_created": 1297313202.517751, "message": "@alex I live in a one story apartment, so no. also, go back to FYAD", "group_id": 81, "id": 64905}, {"user_id": 7, "stars": [{"date_created": 1297884838.9871111, "user_id": 8391}], "topic_id": 1451, "date_created": 1297313009.8355711, "message": "@coderanger BTW if you're responsible for sprints, please put pypy and django in the same room", "group_id": 81, "id": 64865}, {"user_id": 4156, "stars": [], "topic_id": 1451, "date_created": 1297313211.8769231, "message": "Man I can't even do injokes correctly. Must be bedtime.", "group_id": 81, "id": 64908}, {"user_id": 1736, "stars": [], "topic_id": 1451, "date_created": 1297313507.861733, "message": "@alex Roger, though I'm sure you'll have to remind me closer to the con :-)", "group_id": 81, "id": 64972}, {"user_id": 4156, "stars": [], "topic_id": 1451, "date_created": 1297312943.4032979, "message": "I'll be there pretty much the whole time, I think, thanks to my awesome employer. Will probably have to schedule a Fabric sprint sometime...", "group_id": 81, "id": 64854}, {"user_id": 4156, "stars": [{"date_created": 1297313057.106899, "user_id": 3019}, {"date_created": 1297313125.2063611, "user_id": 3946}], "topic_id": 1451, "date_created": 1297313042.0011401, "message": "@sshirokov goon spotted\u00bf", "group_id": 81, "id": 64873}, {"user_id": 7, "stars": [], "topic_id": 1451, "date_created": 1297313065.2304261, "message": "@bitprophet do you have stairs in your house?", "group_id": 81, "id": 64878}, {"user_id": 205, "stars": [], "topic_id": 1451, "date_created": 1297318170.601258, "message": "I might need to find a place to crash for Sunday/Monday night. If anyone has those awkward days available (or floor space :)", "group_id": 81, "id": 66148}, {"user_id": 6439, "stars": [], "topic_id": 1451, "date_created": 1297377073.143131, "message": "I'll be there also", "group_id": 81, "id": 75497}, {"user_id": 228, "stars": [{"date_created": 1297387428.463892, "user_id": 1376}], "topic_id": 1451, "date_created": 1297376999.583405, "message": "party at @acdha on sunday night!!", "group_id": 81, "id": 75492}, {"user_id": 927, "stars": [], "topic_id": 1451, "date_created": 1297376057.143158, "message": "Eric: almost certain that I will", "group_id": 81, "id": 75376}, {"user_id": 6431, "stars": [], "topic_id": 1451, "date_created": 1297377147.58074, "message": "I'm there for conference and sprinting on Django after through midday 3/17", "group_id": 81, "id": 75502}, {"user_id": 228, "stars": [], "topic_id": 1451, "date_created": 1297377226.5678699, "message": "@frankwiles i'm going to be hunting you down and offering beer and food.", "group_id": 81, "id": 75506}, {"user_id": 7, "stars": [], "topic_id": 1451, "date_created": 1297378056.3063631, "message": "@jacob I don't remembre what a gastropub is, but the one we went to last year was delicious", "group_id": 81, "id": 75591}, {"user_id": 228, "stars": [], "topic_id": 1451, "date_created": 1297377196.753022, "message": "i can't decide if i want to be a neophyte sprinting on pypy or django", "group_id": 81, "id": 75505}, {"user_id": 7, "stars": [], "topic_id": 1451, "date_created": 1297377229.2194009, "message": "@jacob they'll hopefully be in the same room :)", "group_id": 81, "id": 75507}, {"user_id": 6439, "stars": [{"date_created": 1297377597.557447, "user_id": 1}, {"date_created": 1297377989.8627751, "user_id": 228}], "topic_id": 1451, "date_created": 1297377287.7524641, "message": "@jacob If you have beer and food, I'll likely find you first! :)", "group_id": 81, "id": 75515}, {"user_id": 2, "stars": [], "topic_id": 1451, "date_created": 1297379208.4420071, "message": "mmmm pub", "group_id": 81, "id": 75746}, {"user_id": 2, "stars": [{"date_created": 1297381668.9494591, "user_id": 1}], "topic_id": 1451, "date_created": 1297379780.646404, "message": "but I'm sad to be missing pycon", "group_id": 81, "id": 75879}, {"user_id": 228, "stars": [], "topic_id": 1451, "date_created": 1297378021.4734371, "message": "@frankwiles @ericflo let's find a night(or two or five) to gastropub+talk about pgsql", "group_id": 81, "id": 75585}, {"user_id": 1, "stars": [], "topic_id": 1451, "date_created": 1297378908.5906229, "message": "I'm in", "group_id": 81, "id": 75687}, {"user_id": 1736, "stars": [], "topic_id": 1451, "date_created": 1297379732.185699, "message": "@leah I thought you had gone over to the SXSW dark side :-P", "group_id": 81, "id": 75870}, {"user_id": 2, "stars": [{"date_created": 1297381667.1457191, "user_id": 1}], "topic_id": 1451, "date_created": 1297379773.236557, "message": "@coderanger yeah, I'm going to sxsw", "group_id": 81, "id": 75876}, {"user_id": 3354, "stars": [], "topic_id": 1451, "date_created": 1297384607.2771161, "message": "I am hoping to have an Open Space event on the Saturday night that I have given the working title \"Good Stevening: An Evening with the PSF Chairman\". Not exactly a scintillating title, but I am hoping that some entertaining discussions will ensue.", "group_id": 81, "id": 76588}, {"user_id": 3354, "stars": [], "topic_id": 1451, "date_created": 1297384649.613219, "message": "And they aren't limited to the PSF, or even to Python: Life, the Universe and Everything are all acceptable topics.", "group_id": 81, "id": 76590}, {"user_id": 205, "stars": [], "topic_id": 1451, "date_created": 1297388760.0837369, "message": "@acdha Awesome. Do I need to confirm in any way? Or just show up on your doorstep? :)", "group_id": 81, "id": 77339}, {"user_id": 4893, "stars": [], "topic_id": 1451, "date_created": 1297422625.6916921, "message": "Sadly, I'll miss PyCon and DjangoCon but perhaps I can make it to OSCON :-)", "group_id": 81, "id": 79457}, {"user_id": 4120, "stars": [], "topic_id": 1451, "date_created": 1297429415.8544691, "message": "I'm planning to go. I haven't registered yet.", "group_id": 81, "id": 80177}, {"user_id": 4120, "stars": [], "topic_id": 1451, "date_created": 1297429460.227272, "message": "Anybody considering driving?", "group_id": 81, "id": 80180}, {"user_id": 927, "stars": [], "topic_id": 1451, "date_created": 1297437916.6304009, "message": "@ericholscher I'll get in touch once I get the final reservation confirmation (it's approved so that should be a formality)", "group_id": 81, "id": 80782}, {"user_id": 521, "stars": [], "topic_id": 1451, "date_created": 1297442420.861001, "message": "@leah I thought I was the only one going to sxsw over pycon this year ;)", "group_id": 81, "id": 81380}, {"user_id": 6439, "stars": [], "topic_id": 1451, "date_created": 1297453605.8725281, "message": "@jacob I'm in", "group_id": 81, "id": 82657}, {"user_id": 1398, "stars": [], "topic_id": 1451, "date_created": 1297464063.8660359, "message": "I'll be there. I'm speaking about packages and django. But not like Tarique.", "group_id": 81, "id": 84467}, {"user_id": 207, "stars": [], "topic_id": 1451, "date_created": 1297474316.0593541, "message": "anybody looking for a roommate?", "group_id": 81, "id": 84968}, {"user_id": 207, "stars": [], "topic_id": 1451, "date_created": 1297474308.511817, "message": "so it looks like i'll be able to make it!", "group_id": 81, "id": 84966}, {"user_id": 7376, "stars": [], "topic_id": 1451, "date_created": 1297474355.9000151, "message": "@gulopine I might, I haven't decided if I'm going yet though", "group_id": 81, "id": 84971}, {"user_id": 4156, "stars": [], "topic_id": 1451, "date_created": 1297481293.3508871, "message": "@Gulopine woo!", "group_id": 81, "id": 85629}, {"user_id": 7, "stars": [], "topic_id": 1451, "date_created": 1297482429.096422, "message": "talks have already been accepted by the program committee", "group_id": 81, "id": 85777}, {"user_id": 4219, "stars": [], "topic_id": 1451, "date_created": 1297482370.969924, "message": "is there a voting process for speakers?", "group_id": 81, "id": 85764}, {"user_id": 1736, "stars": [], "topic_id": 1451, "date_created": 1297492901.685864, "message": "But to answer the question more, yes, community members volunteer to be on the program committee which votes on talks (not speakers).", "group_id": 81, "id": 86307}, {"user_id": 723, "stars": [{"date_created": 1297498626.2803719, "user_id": 1}], "topic_id": 1451, "date_created": 1297498484.545583, "message": "I'll be at PyCon. If anyone wants to hack on redis-py, let me know!", "group_id": 81, "id": 86416}, {"user_id": 212, "stars": [], "topic_id": 1451, "date_created": 1297537294.2610891, "message": "@Gulopine it looks like one of the guys from my room isn't going to be there after all, so we still need another roommie! drop me an email: g@briel.ca", "group_id": 81, "id": 87330}, {"user_id": 3347, "stars": [], "topic_id": 1451, "date_created": 1297884269.72927, "message": "I'll be there for the conference days and two sprint days.", "group_id": 81, "id": 123140}, {"user_id": 8391, "stars": [], "topic_id": 1451, "date_created": 1297884714.715544, "message": "I'm pumped for pycon", "group_id": 81, "id": 123266}, {"user_id": 228, "stars": [], "topic_id": 1451, "date_created": 1297886726.972841, "message": "@gulopine @gg's room is the legit room to be at. true story", "group_id": 81, "id": 123578}, {"user_id": 8391, "stars": [{"date_created": 1297906378.3475921, "user_id": 1}], "topic_id": 1451, "date_created": 1297906246.5064189, "message": "hell yes", "group_id": 81, "id": 128096}, {"user_id": 8391, "stars": [], "topic_id": 1451, "date_created": 1297907161.4628191, "message": "maybe just audio", "group_id": 81, "id": 128280}, {"user_id": 3, "stars": [], "topic_id": 1451, "date_created": 1297906045.5995009, "message": "i'll be there", "group_id": 81, "id": 128053}, {"user_id": 3, "stars": [{"date_created": 1297906376.75653, "user_id": 1}, {"date_created": 1297906498.2826381, "user_id": 8391}, {"date_created": 1297906674.1452639, "user_id": 4156}, {"date_created": 1297914065.5614381, "user_id": 177}, {"date_created": 1297985588.1523759, "user_id": 844}], "topic_id": 1451, "date_created": 1297906062.321116, "message": "github drinkup is imminent", "group_id": 81, "id": 128056}, {"user_id": 4156, "stars": [{"date_created": 1297906692.5216041, "user_id": 8391}], "topic_id": 1451, "date_created": 1297906678.195183, "message": "schweet", "group_id": 81, "id": 128166}, {"user_id": 1, "stars": [{"date_created": 1297908087.4337101, "user_id": 8391}], "topic_id": 1451, "date_created": 1297907184.625236, "message": "@kennethreitz That would/will be awesome!", "group_id": 81, "id": 128281}, {"user_id": 8391, "stars": [], "topic_id": 1451, "date_created": 1297907038.2041919, "message": "I'm going to (maybe) be recording a few video mini-interviews for the changelog", "group_id": 81, "id": 128266}, {"user_id": 8391, "stars": [], "topic_id": 1451, "date_created": 1297907943.2954371, "message": "@defunkt I hope it'll be on a conference day", "group_id": 81, "id": 128381}, {"user_id": 8391, "stars": [], "topic_id": 1451, "date_created": 1297907214.609066, "message": "Maybe even a few tshirts and stickers for some lucky peeps ;)", "group_id": 81, "id": 128286}, {"user_id": 1736, "stars": [], "topic_id": 1451, "date_created": 1297908301.5099559, "message": "@alex We'll just put you on @jessenoller's shoulders, it'l be fine", "group_id": 81, "id": 128448}, {"user_id": 4156, "stars": [{"date_created": 1298141992.2339621, "user_id": 8391}], "topic_id": 1451, "date_created": 1297908239.842675, "message": "@kennethreitz oh god I'm going to embarrass the heck out of myself aren't I", "group_id": 81, "id": 128433}, {"user_id": 7, "stars": [], "topic_id": 1451, "date_created": 1297908166.5839031, "message": "@defunkt github drink water up please", "group_id": 81, "id": 128423}, {"user_id": 2024, "stars": [{"date_created": 1297955581.832181, "user_id": 4156}], "topic_id": 1451, "date_created": 1297946302.3917339, "message": "@bitprophet it's not embarrassing if we're all doing it. Right?", "group_id": 81, "id": 131228}, {"user_id": 8391, "stars": [], "topic_id": 1451, "date_created": 1298142003.030442, "message": "@bitprophet we'll see :)", "group_id": 81, "id": 150198}]