[{"user_id": 1775, "stars": [], "topic_id": 36812, "date_created": 1306363930.553946, "message": "You rock. Thank you so much!", "group_id": 109, "id": 1185157}, {"user_id": 12179, "stars": [], "topic_id": 36812, "date_created": 1306363643.673892, "message": "but up to now no official api nor any other clients. The main site is not really usable on a small smartphone screen.", "group_id": 109, "id": 1185116}, {"user_id": 12179, "stars": [], "topic_id": 36812, "date_created": 1306363620.4114759, "message": "There's an iOS app: http://itunes.apple.com/us/app/teuxdeux/id384291782", "group_id": 109, "id": 1185113}, {"user_id": 12179, "stars": [], "topic_id": 36812, "date_created": 1306363658.00138, "message": "so I decided to reverse-engineer the API, and here's what I got:", "group_id": 109, "id": 1185118}, {"user_id": 12179, "stars": [], "topic_id": 36812, "date_created": 1306363605.866564, "message": "So maybe you heard of TeuxDeux: http://teuxdeux.com, a \"simple, designy, free, browser-based to-do app\".", "group_id": 109, "id": 1185109}, {"user_id": 12179, "stars": [{"date_created": 1306388005.3803921, "user_id": 1516}, {"date_created": 1306441160.892277, "user_id": 19808}, {"date_created": 1306503735.532234, "user_id": 5928}], "topic_id": 36812, "date_created": 1306363681.73068, "message": "A complete documentation of the API used by the iOS app: https://github.com/badboy/teuxdeux/wiki/API", "group_id": 109, "id": 1185124}, {"user_id": 12179, "stars": [{"date_created": 1306441164.7379739, "user_id": 19808}, {"date_created": 1306503761.9620891, "user_id": 5928}], "topic_id": 36812, "date_created": 1306363692.517091, "message": "and of course I built an small API client library in ruby: https://github.com/badboy/teuxdeux", "group_id": 109, "id": 1185127}, {"user_id": 12179, "stars": [], "topic_id": 36812, "date_created": 1306407131.675936, "message": "=D thanks.", "group_id": 109, "id": 1190909}, {"user_id": 19808, "stars": [], "topic_id": 36812, "date_created": 1306441145.8768649, "message": "Ooh, very clever. I really like TeuxDeux so will be sure to check out what you've done. Thanks!", "group_id": 109, "id": 1195604}, {"user_id": 34979, "stars": [], "topic_id": 36812, "date_created": 1307112395.873944, "message": "*first language.", "group_id": 109, "id": 1277945}, {"user_id": 34979, "stars": [], "topic_id": 36812, "date_created": 1307112383.0979381, "message": "@teuxdeux Not be nasty, as English may not be your fist language, but its \"unofficial\" not \"inofficial\".", "group_id": 109, "id": 1277942}, {"user_id": 12179, "stars": [], "topic_id": 36812, "date_created": 1307115767.534214, "message": "oops. I typed it everywhere else correct. Just this mistake over here :D", "group_id": 109, "id": 1278386}, {"user_id": 12179, "stars": [{"date_created": 1307229080.9067409, "user_id": 19808}], "topic_id": 36812, "date_created": 1307115825.128999, "message": "oh, and btw, I made a small webapp for use on a smartphone: https://github.com/badboy/teuxdeux-webapp", "group_id": 109, "id": 1278392}, {"user_id": 34979, "stars": [], "topic_id": 36812, "date_created": 1307118012.5839989, "message": "@badboy fair enough.", "group_id": 109, "id": 1278636}]