[{"name": "Getting the story and characters straight", "slug": "getting-the-story-and-characters-straight", "creator_id": 25, "date_created": 1302960303.166383, "group_id": 8925, "id": 19823}, {"name": "First episode this Sunday!", "slug": "first-episode-this-sunday", "creator_id": 2, "date_created": 1302839099.030772, "group_id": 8925, "id": 19560}, {"name": "Who's your favorite character?", "slug": "whos-your-favorite-character", "creator_id": 2, "date_created": 1302839678.663933, "group_id": 8925, "id": 19562}, {"name": "That did not take long: Game of Thrones picked up for another season.", "slug": "that-did-not-take-long-game-of-thrones-picked-up-for-another-season", "creator_id": 5, "date_created": 1303250211.8390651, "group_id": 8925, "id": 20427}, {"name": "Watching Game of Thrones", "slug": "watching-game-of-thrones", "creator_id": 25, "date_created": 1303319419.919987, "group_id": 8925, "id": 20544}, {"name": "Ep. 2 The Kingsroad", "slug": "ep-2-the-kingsroad", "creator_id": 25, "date_created": 1303679565.6878381, "group_id": 8925, "id": 21135}, {"name": "Welcome to Game of Thrones", "slug": "welcome-to-game-of-thrones", "creator_id": 14034, "date_created": 1304121200.466677, "group_id": 8925, "id": 32402}, {"name": "Read the books first or start with the show?", "slug": "read-the-books-first-or-start-with-the-show", "creator_id": 1, "date_created": 1302886974.855432, "group_id": 8925, "id": 19667}, {"name": "Ep. 3 Lord Snow", "slug": "ep-3-lord-snow", "creator_id": 25, "date_created": 1304279355.220778, "group_id": 8925, "id": 33082}, {"name": "How does the episode match up with the chapters?", "slug": "how-does-the-episode-match-up-with-the-chapters", "creator_id": 1516, "date_created": 1304321591.8383241, "group_id": 8925, "id": 33142}, {"name": "Ep. 4 Cripples, Bastards and Broken Things", "slug": "ep-4-cripples-bastards-and-broken-things", "creator_id": 25, "date_created": 1304880241.8514769, "group_id": 8925, "id": 34263}, {"name": "Ep. 5 The Wolf and the Lion", "slug": "ep-5-the-wolf-and-the-lion", "creator_id": 1516, "date_created": 1305533629.4632449, "group_id": 8925, "id": 35468}, {"name": "Episode 6", "slug": "episode-6", "creator_id": 22669, "date_created": 1306874782.003577, "group_id": 8925, "id": 37587}, {"name": "Ep. 9 Baelor", "slug": "ep-9-baelor", "creator_id": 2691, "date_created": 1307982414.3094709, "group_id": 8925, "id": 39202}, {"name": "Episode 10 - Season Finale", "slug": "episode-10-season-finale", "creator_id": 22669, "date_created": 1308713783.171041, "group_id": 8925, "id": 40075}]